hypergumbo_lang_common/__init__.py
hypergumbo_lang_common/astro.py
hypergumbo_lang_common/clojure.py
hypergumbo_lang_common/commonlisp.py
hypergumbo_lang_common/cuda.py
hypergumbo_lang_common/dart.py
hypergumbo_lang_common/elixir.py
hypergumbo_lang_common/elm.py
hypergumbo_lang_common/erlang.py
hypergumbo_lang_common/fortran.py
hypergumbo_lang_common/fsharp.py
hypergumbo_lang_common/glsl.py
hypergumbo_lang_common/graphql.py
hypergumbo_lang_common/haskell.py
hypergumbo_lang_common/hcl.py
hypergumbo_lang_common/hlsl.py
hypergumbo_lang_common/julia.py
hypergumbo_lang_common/latex.py
hypergumbo_lang_common/matlab.py
hypergumbo_lang_common/meson.py
hypergumbo_lang_common/nix.py
hypergumbo_lang_common/ocaml.py
hypergumbo_lang_common/proto.py
hypergumbo_lang_common/puppet.py
hypergumbo_lang_common/purescript.py
hypergumbo_lang_common/r_lang.py
hypergumbo_lang_common/racket.py
hypergumbo_lang_common/robot.py
hypergumbo_lang_common/rst.py
hypergumbo_lang_common/scheme.py
hypergumbo_lang_common/scss.py
hypergumbo_lang_common/starlark.py
hypergumbo_lang_common/svelte.py
hypergumbo_lang_common/thrift.py
hypergumbo_lang_common/vue.py
hypergumbo_lang_common/wgsl.py
hypergumbo_lang_common-2.0.0.dist-info/METADATA
hypergumbo_lang_common-2.0.0.dist-info/WHEEL
hypergumbo_lang_common-2.0.0.dist-info/entry_points.txt
hypergumbo_lang_common-2.0.0.dist-info/RECORD
