Metadata-Version: 2.4
Name: hypergumbo-lang-common
Version: 2.0.0
Summary: Common domain-specific language analyzers for hypergumbo
Author: Hypergumbo contributors
License: AGPL-3.0-or-later
Keywords: code-graph,language-support,static-analysis
Classifier: Development Status :: 3 - Alpha
Classifier: License :: OSI Approved :: GNU Affero General Public License v3 or later (AGPLv3+)
Classifier: Programming Language :: Python :: 3
Classifier: Programming Language :: Python :: 3 :: Only
Requires-Python: >=3.10
Requires-Dist: hypergumbo-core==2.0.0
Requires-Dist: tree-sitter-commonlisp>=0.4
Requires-Dist: tree-sitter-cuda>=0.20
Requires-Dist: tree-sitter-fortran>=0.1
Requires-Dist: tree-sitter-glsl>=0.1
Requires-Dist: tree-sitter-graphql>=0.1
Requires-Dist: tree-sitter-haskell>=0.21
Requires-Dist: tree-sitter-hcl>=1.2
Requires-Dist: tree-sitter-julia>=0.23
Requires-Dist: tree-sitter-language-pack>=0.13
Requires-Dist: tree-sitter-nix>=0.1
Requires-Dist: tree-sitter-ocaml>=0.21
Requires-Dist: tree-sitter-robot>=1.1
